deepchecks_client/__init__.py
deepchecks_client/_shared_docs.py
deepchecks_client/core/AmazonRootCA1.cer
deepchecks_client/core/__init__.py
deepchecks_client/core/api.py
deepchecks_client/core/client.py
deepchecks_client/core/utils.py
deepchecks_client/tabular/__init__.py
deepchecks_client/tabular/client.py
deepchecks_client/tabular/utils.py
deepchecks_client-0.19.2.dist-info/METADATA
deepchecks_client-0.19.2.dist-info/WHEEL
deepchecks_client-0.19.2.dist-info/top_level.txt
deepchecks_client-0.19.2.dist-info/RECORD
