Metadata-Version: 2.1
Name: deepchecks-client
Version: 0.19.2
Summary: The SDK client for communicating with Deepchecks monitoring service
Author: deepchecks
Author-email: info@deepchecks.com
Requires-Python: >=3.6
Requires-Dist: numpy
Requires-Dist: pandas
Requires-Dist: deepchecks
Requires-Dist: httpx>=0.23.0
Requires-Dist: pendulum==2.1.2
Requires-Dist: fastjsonschema==2.16.2
Requires-Dist: termcolor
Requires-Dist: PyYAML
Requires-Dist: pip-system-certs>=3.1
Requires-Dist: typing-extensions<5,>=4.11.0
Requires-Dist: rfc3339-validator==0.1.4
Requires-Dist: packaging==23.0
Requires-Dist: importlib-metadata; python_version < "3.8"
